core/__init__.py
core/setup.py
core/ui.py
core/utils.py
core/methods/__init__.py
core/methods/http.py
core/methods/syn.py
core/methods/udp.py
hellflood-1.0.0.dist-info/METADATA
hellflood-1.0.0.dist-info/WHEEL
hellflood-1.0.0.dist-info/entry_points.txt
hellflood-1.0.0.dist-info/top_level.txt
hellflood-1.0.0.dist-info/RECORD
