Metadata-Version: 2.4
Name: hellflood
Version: 1.0.0
Summary: Advanced DDOS Stress Testing Tool (For Educational Use Only)
Home-page: https://github.com/iTs-GoJo/HellFlood
Author: Ali Jafari
Author-email: thealiapi@gmail.com
Keywords: ddos stress-test network security pentest
Classifier: Development Status :: 3 - Alpha
Classifier: Intended Audience :: Education
Classifier: Topic :: Security
Classifier: License :: OSI Approved :: MIT License
Classifier: Programming Language :: Python :: 3
Requires-Python: >=3.6
Dynamic: author
Dynamic: author-email
Dynamic: classifier
Dynamic: description
Dynamic: description-content-type
Dynamic: home-page
Dynamic: keywords
Dynamic: requires-python
Dynamic: summary
